Metadata-Version: 2.1
Name: collector_ring_buffer
Version: 0.0.1
Summary: Ring Buffer para controlar latencia
Home-page: http://gitlab.csn.uchile.cl/dpineda/collector
Author: David Pineda Osorio
Author-email: dpineda@csn.uchile.cl
License: MIT
Keywords: collector,buffer,control
Platform: UNKNOWN
